gisapi/__init__.py
gisapi/client.py
GISAPI_SDK-0.1.5.dist-info/LICENSE
GISAPI_SDK-0.1.5.dist-info/METADATA
GISAPI_SDK-0.1.5.dist-info/WHEEL
GISAPI_SDK-0.1.5.dist-info/top_level.txt
GISAPI_SDK-0.1.5.dist-info/RECORD
